pyntb/__init__.py
pyntb/geoutils.py
pyntb/optimize.py
pyntb/polynomial.py
pyntb-2026.1.0.dist-info/licenses/LICENSE
pyntb-2026.1.0.dist-info/METADATA
pyntb-2026.1.0.dist-info/WHEEL
pyntb-2026.1.0.dist-info/top_level.txt
pyntb-2026.1.0.dist-info/RECORD
