Metadata-Version: 2.4
Name: Pyntb
Version: 2026.1.0
Summary: A toolbox to factorize some code utilities across various projects.
Author-email: Mews Labs <emmanuel.cieren@mews-labs.com>
License-Expression: Apache-2.0
Project-URL: Homepage, https://github.com/eurobios-mews-labs/pyntb
Classifier: Programming Language :: Python :: 3 :: Only
Classifier: Operating System :: OS Independent
Requires-Python: <3.15,>=3.11
License-File: LICENSE
Requires-Dist: numpy>=2.0.1
Requires-Dist: scipy>=1.16.0
Provides-Extra: examples
Requires-Dist: matplotlib; extra == "examples"
Requires-Dist: scikit-learn; extra == "examples"
Provides-Extra: test
Requires-Dist: pytest; extra == "test"
Requires-Dist: scikit-learn; extra == "test"
Requires-Dist: pylint; extra == "test"
Provides-Extra: lint
Requires-Dist: black; extra == "lint"
Provides-Extra: dev
Requires-Dist: pyntb[examples,lint,test]; extra == "dev"
Dynamic: license-file
